quantecon_book_theme/__init__.py
quantecon_book_theme/assets/scripts/index.js
quantecon_book_theme/assets/styles/_breakpoints.scss
quantecon_book_theme/assets/styles/_code.scss
quantecon_book_theme/assets/styles/_colors.scss
quantecon_book_theme/assets/styles/_dropdown.scss
quantecon_book_theme/assets/styles/_html5boilerplate.scss
quantecon_book_theme/assets/styles/_margin.scss
quantecon_book_theme/assets/styles/_normalize.scss
quantecon_book_theme/assets/styles/_quantecon-defaults.scss
quantecon_book_theme/assets/styles/_rtl.scss
quantecon_book_theme/assets/styles/_syntax.scss
quantecon_book_theme/assets/styles/_tippy-themes.scss
quantecon_book_theme/assets/styles/index.scss
quantecon_book_theme/launch.py
quantecon_book_theme/theme/quantecon_book_theme/layout.html
quantecon_book_theme/theme/quantecon_book_theme/static/.gitignore
quantecon_book_theme/theme/quantecon_book_theme/static/scripts/_sphinx_javascript_frameworks_compat.js
quantecon_book_theme/theme/quantecon_book_theme/static/scripts/jquery.js
quantecon_book_theme/theme/quantecon_book_theme/static/scripts/quantecon-book-theme.js
quantecon_book_theme/theme/quantecon_book_theme/static/scripts/quantecon-book-theme.js.map
quantecon_book_theme/theme/quantecon_book_theme/static/styles/quantecon-book-theme.css
quantecon_book_theme/theme/quantecon_book_theme/static/styles/quantecon-book-theme.css.map
quantecon_book_theme/theme/quantecon_book_theme/theme.conf
quantecon_book_theme-0.10.1.dist-info/LICENSE
quantecon_book_theme-0.10.1.dist-info/METADATA
quantecon_book_theme-0.10.1.dist-info/WHEEL
quantecon_book_theme-0.10.1.dist-info/entry_points.txt
quantecon_book_theme-0.10.1.dist-info/RECORD