Metadata-Version: 2.1
Name: quantecon-book-theme
Version: 0.10.1
Summary: A clean book theme for scientific explanations and documentation with Sphinx
Maintainer-Email: Executable Books Team <executablebooks@gmail.com>
License: BSD 3-Clause License
Classifier: Development Status :: 4 - Beta
Classifier: Programming Language :: Python :: 3
Classifier: Framework :: Sphinx
Classifier: Framework :: Sphinx :: Theme
Classifier: License :: OSI Approved :: BSD License
Classifier: Operating System :: OS Independent
Project-URL: Repository, https://github.com/QuantEcon/quantecon-book-theme
Requires-Python: >=3.12
Requires-Dist: pyyaml
Requires-Dist: sphinx<9,>=7
Requires-Dist: docutils
Requires-Dist: click
Requires-Dist: libsass~=0.23.0
Requires-Dist: sphinx_book_theme~=1.1.4
Requires-Dist: beautifulsoup4
Provides-Extra: code-style
Requires-Dist: flake8<3.8.0,>=3.7.0; extra == "code-style"
Requires-Dist: black; extra == "code-style"
Requires-Dist: pre-commit; extra == "code-style"
Provides-Extra: doc
Requires-Dist: folium; extra == "doc"
Requires-Dist: numpy; extra == "doc"
Requires-Dist: matplotlib; extra == "doc"
Requires-Dist: ipywidgets; extra == "doc"
Requires-Dist: pandas; extra == "doc"
Requires-Dist: nbclient; extra == "doc"
Requires-Dist: myst-nb; extra == "doc"
Requires-Dist: sphinx-togglebutton>=0.2.1; extra == "doc"
Requires-Dist: sphinx-thebe; extra == "doc"
Requires-Dist: sphinx-copybutton; extra == "doc"
Requires-Dist: docutils>=0.20; extra == "doc"
Requires-Dist: plotly; extra == "doc"
Requires-Dist: sphinxcontrib-bibtex<=2.5.0,>=2.2.0; extra == "doc"
Provides-Extra: test
Requires-Dist: myst_nb; extra == "test"
Requires-Dist: coverage; extra == "test"
Requires-Dist: pytest; extra == "test"
Requires-Dist: pytest-cov; extra == "test"
Requires-Dist: beautifulsoup4; extra == "test"
Requires-Dist: sphinx_thebe; extra == "test"
Requires-Dist: pytest-regressions; extra == "test"
Requires-Dist: sphinx_copybutton; extra == "test"
Requires-Dist: sphinx_togglebutton; extra == "test"
